{"expireTime":9007200830089689000,"key":"transformer-remark-markdown-html-ast-dd1b833ea7ef4b61dbd5e4a13d5eb457-gatsby-remark-prismjsgatsby-remark-images-","val":{"type":"root","children":[{"type":"element","tagName":"h2","properties":{},"children":[{"type":"text","value":"Webpack의 정의","position":{"start":{"line":1,"column":3,"offset":2},"end":{"line":1,"column":14,"offset":13}}}],"position":{"start":{"line":1,"column":1,"offset":0},"end":{"line":1,"column":14,"offset":13}}},{"type":"text","value":"\n"},{"type":"element","tagName":"p","properties":{},"children":[{"type":"text","value":"-웹어플리케이션을 위해 사용하는 모듈 번들러라는 도구.","position":{"start":{"line":2,"column":1,"offset":14},"end":{"line":2,"column":31,"offset":44}}},{"type":"element","tagName":"br","properties":{},"children":[],"position":{"start":{"line":2,"column":31,"offset":44},"end":{"line":3,"column":1,"offset":47}}},{"type":"text","value":"\n"},{"type":"text","value":"웹팩은 모듈간의 의존관계를 해석한 후에 의존성 그래프를 만들어 모듈들을 해석하고 번들링을 하는 과정을 진행한다.\n이과정은 파일별로 쪼개진 모듈들의 내용을 번들 파일 내에 모두 담는 과정을 의미한다.","position":{"start":{"line":3,"column":1,"offset":47},"end":{"line":4,"column":48,"offset":157}}}],"position":{"start":{"line":2,"column":1,"offset":14},"end":{"line":4,"column":48,"offset":157}}},{"type":"text","value":"\n"},{"type":"element","tagName":"h3","properties":{},"children":[{"type":"text","value":"Entry란?","position":{"start":{"line":6,"column":4,"offset":162},"end":{"line":6,"column":11,"offset":169}}}],"position":{"start":{"line":6,"column":1,"offset":159},"end":{"line":6,"column":11,"offset":169}}},{"type":"text","value":"\n"},{"type":"element","tagName":"p","properties":{},"children":[{"type":"text","value":"-모듈의 의존 관계를 이해하기 위한 시작점을 설정.","position":{"start":{"line":7,"column":1,"offset":170},"end":{"line":7,"column":29,"offset":198}}}],"position":{"start":{"line":7,"column":1,"offset":170},"end":{"line":7,"column":29,"offset":198}}},{"type":"text","value":"\n"},{"type":"element","tagName":"h3","properties":{},"children":[{"type":"text","value":"Output이란?","position":{"start":{"line":9,"column":4,"offset":203},"end":{"line":9,"column":13,"offset":212}}}],"position":{"start":{"line":9,"column":1,"offset":200},"end":{"line":9,"column":13,"offset":212}}},{"type":"text","value":"\n"},{"type":"element","tagName":"p","properties":{},"children":[{"type":"text","value":"-Webpack이 생성하는 번들 파일에 대한 정보를 설정.","position":{"start":{"line":10,"column":1,"offset":213},"end":{"line":10,"column":33,"offset":245}}}],"position":{"start":{"line":10,"column":1,"offset":213},"end":{"line":10,"column":33,"offset":245}}},{"type":"text","value":"\n"},{"type":"element","tagName":"h3","properties":{},"children":[{"type":"text","value":"예제로 이해하기","position":{"start":{"line":12,"column":4,"offset":250},"end":{"line":12,"column":12,"offset":258}}}],"position":{"start":{"line":12,"column":1,"offset":247},"end":{"line":12,"column":12,"offset":258}}},{"type":"text","value":"\n"},{"type":"element","tagName":"p","properties":{},"children":[{"type":"text","value":"모듈에 대한 내용을 진행 할 폴더에서 ","position":{"start":{"line":14,"column":1,"offset":260},"end":{"line":14,"column":22,"offset":281}}}],"position":{"start":{"line":14,"column":1,"offset":260},"end":{"line":14,"column":22,"offset":281}}},{"type":"text","value":"\n"},{"type":"raw","value":"<div class=\"gatsby-highlight\" data-language=\"shellscript\"><pre class=\"language-shellscript\"><code class=\"language-shellscript\">$ npm init -y</code></pre></div>","position":{"start":{"line":15,"column":1,"offset":282},"end":{"line":17,"column":4,"offset":315}}},{"type":"text","value":"\n"},{"type":"element","tagName":"p","properties":{},"children":[{"type":"text","value":"console에 json에 대한 내용이 출력되고 package.json 파일이 생성된다.","position":{"start":{"line":18,"column":1,"offset":316},"end":{"line":18,"column":50,"offset":365}}},{"type":"element","tagName":"br","properties":{},"children":[],"position":{"start":{"line":18,"column":50,"offset":365},"end":{"line":19,"column":1,"offset":368}}},{"type":"text","value":"\n"},{"type":"text","value":"이 파일은 작업하는 프로젝트에 대한 정보를 나타내고 이 프로젝트가 사용하는 패키지들을 관리해주는 역활을 한다.","position":{"start":{"line":19,"column":1,"offset":368},"end":{"line":19,"column":62,"offset":429}}},{"type":"element","tagName":"br","properties":{},"children":[],"position":{"start":{"line":19,"column":62,"offset":429},"end":{"line":20,"column":1,"offset":432}}},{"type":"text","value":"\n"},{"type":"text","value":"또 npm명령어를 통해 복잡한 스크립트를 쉽게 다룰 수 있게 도와 준다.  ","position":{"start":{"line":20,"column":1,"offset":432},"end":{"line":20,"column":43,"offset":474}}}],"position":{"start":{"line":18,"column":1,"offset":316},"end":{"line":20,"column":43,"offset":474}}},{"type":"text","value":"\n"},{"type":"element","tagName":"p","properties":{},"children":[{"type":"text","value":"package.json파일을 살펴 보면 내가 만든 파일의 이름이 name이라는 프로퍼티에 기록된 것을 확인 할 수 있으며,","position":{"start":{"line":22,"column":1,"offset":476},"end":{"line":22,"column":69,"offset":544}}},{"type":"element","tagName":"br","properties":{},"children":[],"position":{"start":{"line":22,"column":69,"offset":544},"end":{"line":23,"column":1,"offset":547}}},{"type":"text","value":"\n"},{"type":"text","value":"프로젝트의 버젼 설명등 다양한 프로젝트에 관한 정보들을 담고 있다.\nname의 기본값은 프로젝트 폴더의 이름으로 만들어진다. 그리고 외부 패키지를 사용하게 되면 이 파일안에 기록한다.","position":{"start":{"line":23,"column":1,"offset":547},"end":{"line":24,"column":65,"offset":649}}}],"position":{"start":{"line":22,"column":1,"offset":476},"end":{"line":24,"column":65,"offset":649}}},{"type":"text","value":"\n"},{"type":"raw","value":"<div class=\"gatsby-highlight\" data-language=\"shellscript\"><pre class=\"language-shellscript\"><code class=\"language-shellscript\">$ npm install webpack webpack-cli --save-dev</code></pre></div>","position":{"start":{"line":26,"column":1,"offset":651},"end":{"line":28,"column":4,"offset":715}}},{"type":"text","value":"\n"},{"type":"element","tagName":"p","properties":{},"children":[{"type":"text","value":"(","position":{"start":{"line":29,"column":1,"offset":716},"end":{"line":29,"column":2,"offset":717}}},{"type":"raw","value":"<code class=\"language-text\">webpack-cli</code>","position":{"start":{"line":29,"column":2,"offset":717},"end":{"line":29,"column":15,"offset":730}}},{"type":"text","value":" : 웹팩을 실행 할 수 있는 명령어들을 지원해주는 패키지를 의미한다.)","position":{"start":{"line":29,"column":15,"offset":730},"end":{"line":29,"column":55,"offset":770}}}],"position":{"start":{"line":29,"column":1,"offset":716},"end":{"line":29,"column":55,"offset":770}}},{"type":"text","value":"\n"},{"type":"element","tagName":"p","properties":{},"children":[{"type":"text","value":"설치가 끝나면 node-modules라는 폴더가 생기고,","position":{"start":{"line":31,"column":1,"offset":772},"end":{"line":31,"column":32,"offset":803}}},{"type":"element","tagName":"br","properties":{},"children":[],"position":{"start":{"line":31,"column":32,"offset":803},"end":{"line":32,"column":1,"offset":806}}},{"type":"text","value":"\n"},{"type":"text","value":"이 안에 webpack과 webpack-cli 패키지 그리고 이 두패키지가 의존하고 있는 다른 패키지들이 모두 설치 되어 있다.  ","position":{"start":{"line":32,"column":1,"offset":806},"end":{"line":32,"column":74,"offset":879}}}],"position":{"start":{"line":31,"column":1,"offset":772},"end":{"line":32,"column":74,"offset":879}}},{"type":"text","value":"\n"},{"type":"element","tagName":"p","properties":{},"children":[{"type":"text","value":"폴더 내부에 package.json파일 안에서 webpack과 webpack-cli이 설치된 것을 볼 수 있다.","position":{"start":{"line":34,"column":1,"offset":881},"end":{"line":34,"column":63,"offset":943}}}],"position":{"start":{"line":34,"column":1,"offset":881},"end":{"line":34,"column":63,"offset":943}}},{"type":"text","value":"\n"},{"type":"element","tagName":"p","properties":{},"children":[{"type":"text","value":"[mathUtil.js]","position":{"start":{"line":36,"column":2,"offset":946},"end":{"line":36,"column":13,"offset":957}}}],"position":{"start":{"line":36,"column":1,"offset":945},"end":{"line":36,"column":14,"offset":958}}},{"type":"text","value":"\n"},{"type":"raw","value":"<div class=\"gatsby-highlight\" data-language=\"javascript\"><pre class=\"language-javascript\"><code class=\"language-javascript\"><span class=\"token keyword\">const</span> <span class=\"token constant\">PI</span> <span class=\"token operator\">=</span> <span class=\"token number\">3.14</span><span class=\"token punctuation\">;</span>\n<span class=\"token keyword\">const</span> <span class=\"token function-variable function\">getCircleArea</span> <span class=\"token operator\">=</span> <span class=\"token parameter\">r</span> <span class=\"token operator\">=></span> r <span class=\"token operator\">*</span> r <span class=\"token operator\">*</span> <span class=\"token constant\">PI</span><span class=\"token punctuation\">;</span>\n<span class=\"token keyword\">const</span> getSquareArea <span class=\"token operator\">=</span> d <span class=\"token operator\">=</span> d <span class=\"token operator\">*</span> d<span class=\"token punctuation\">;</span>\n\nmodule<span class=\"token punctuation\">.</span>exports <span class=\"token operator\">=</span> <span class=\"token punctuation\">{</span>\n    <span class=\"token constant\">PI</span><span class=\"token punctuation\">,</span>\n    getCircleArea<span class=\"token punctuation\">,</span>\n    getSquareArea\n<span class=\"token punctuation\">}</span></code></pre></div>","position":{"start":{"line":37,"column":1,"offset":959},"end":{"line":47,"column":4,"offset":1132}}},{"type":"text","value":"\n"},{"type":"element","tagName":"p","properties":{},"children":[{"type":"text","value":"[log.js]","position":{"start":{"line":48,"column":2,"offset":1134},"end":{"line":48,"column":8,"offset":1140}}}],"position":{"start":{"line":48,"column":1,"offset":1133},"end":{"line":48,"column":9,"offset":1141}}},{"type":"text","value":"\n"},{"type":"raw","value":"<div class=\"gatsby-highlight\" data-language=\"javascript\"><pre class=\"language-javascript\"><code class=\"language-javascript\"><span class=\"token keyword\">const</span> <span class=\"token function-variable function\">logInput</span> <span class=\"token operator\">=</span> <span class=\"token parameter\">input</span> <span class=\"token operator\">=></span> <span class=\"token template-string\"><span class=\"token template-punctuation string\">`</span><span class=\"token string\">입력받은 값 : </span><span class=\"token interpolation\"><span class=\"token interpolation-punctuation punctuation\">${</span>input<span class=\"token interpolation-punctuation punctuation\">}</span></span><span class=\"token template-punctuation string\">`</span></span><span class=\"token punctuation\">;</span>\n<span class=\"token keyword\">const</span> <span class=\"token function-variable function\">logResult</span> <span class=\"token operator\">=</span> <span class=\"token punctuation\">(</span><span class=\"token parameter\">figure<span class=\"token punctuation\">,</span> result</span><span class=\"token punctuation\">)</span> <span class=\"token operator\">=></span> <span class=\"token template-string\"><span class=\"token template-punctuation string\">`</span><span class=\"token interpolation\"><span class=\"token interpolation-punctuation punctuation\">${</span>figure<span class=\"token interpolation-punctuation punctuation\">}</span></span><span class=\"token string\">의 넓이는 : </span><span class=\"token interpolation\"><span class=\"token interpolation-punctuation punctuation\">${</span>result<span class=\"token interpolation-punctuation punctuation\">}</span></span><span class=\"token string\"> 입니다.</span><span class=\"token template-punctuation string\">`</span></span><span class=\"token punctuation\">;</span>\n<span class=\"token keyword\">const</span> logFigureError <span class=\"token operator\">=</span> <span class=\"token string\">\"지원되지 않는 도형입니다. '정사각형' 또는 '원'을 입력해주세요. \\n커맨드 라인을 종료합니다.\"</span><span class=\"token punctuation\">;</span>\n\nmodule<span class=\"token punctuation\">.</span>exports <span class=\"token operator\">=</span> <span class=\"token punctuation\">{</span>\n    logInput<span class=\"token punctuation\">,</span>\n    logResult<span class=\"token punctuation\">,</span>\n    logFigureError\n<span class=\"token punctuation\">}</span></code></pre></div>","position":{"start":{"line":49,"column":1,"offset":1142},"end":{"line":59,"column":4,"offset":1430}}},{"type":"text","value":"\n"},{"type":"element","tagName":"p","properties":{},"children":[{"type":"text","value":"[index.js]","position":{"start":{"line":60,"column":2,"offset":1432},"end":{"line":60,"column":10,"offset":1440}}}],"position":{"start":{"line":60,"column":1,"offset":1431},"end":{"line":60,"column":11,"offset":1441}}},{"type":"text","value":"\n"},{"type":"raw","value":"<div class=\"gatsby-highlight\" data-language=\"javascript\"><pre class=\"language-javascript\"><code class=\"language-javascript\"><span class=\"token keyword\">const</span> readline <span class=\"token operator\">=</span> <span class=\"token function\">require</span><span class=\"token punctuation\">(</span><span class=\"token string\">\"readline\"</span><span class=\"token punctuation\">)</span><span class=\"token punctuation\">;</span>\n<span class=\"token keyword\">const</span> rl <span class=\"token operator\">=</span> readline<span class=\"token punctuation\">.</span><span class=\"token function\">createInterface</span><span class=\"token punctuation\">(</span><span class=\"token punctuation\">{</span>\n    input<span class=\"token punctuation\">:</span> process<span class=\"token punctuation\">.</span>stdin<span class=\"token punctuation\">,</span>\n    output<span class=\"token punctuation\">:</span> process<span class=\"token punctuation\">.</span>stdout\n<span class=\"token punctuation\">}</span><span class=\"token punctuation\">)</span><span class=\"token punctuation\">;</span>\n\n<span class=\"token keyword\">const</span> <span class=\"token punctuation\">{</span> getCircleArea<span class=\"token punctuation\">,</span> getSquareArea <span class=\"token punctuation\">}</span> <span class=\"token operator\">=</span> <span class=\"token function\">require</span><span class=\"token punctuation\">(</span><span class=\"token string\">'./mathUtil'</span><span class=\"token punctuation\">)</span><span class=\"token punctuation\">;</span>\n<span class=\"token keyword\">const</span> <span class=\"token punctuation\">{</span> logFigureError<span class=\"token punctuation\">,</span> logInput<span class=\"token punctuation\">,</span> logResult <span class=\"token punctuation\">}</span> <span class=\"token operator\">=</span> <span class=\"token function\">require</span><span class=\"token punctuation\">(</span><span class=\"token string\">'./log'</span><span class=\"token punctuation\">)</span><span class=\"token punctuation\">;</span>\n\nrl<span class=\"token punctuation\">.</span><span class=\"token function\">question</span><span class=\"token punctuation\">(</span>\n    <span class=\"token string\">\"넓이를 구하고자 하는 도형의 종류를 입력해주세요. ( 정사각형, 원) :\"</span><span class=\"token punctuation\">,</span> \n    <span class=\"token parameter\">figure</span> <span class=\"token operator\">=></span> <span class=\"token punctuation\">{</span>\n    console<span class=\"token punctuation\">.</span><span class=\"token function\">log</span> <span class=\"token punctuation\">(</span><span class=\"token template-string\"><span class=\"token template-punctuation string\">`</span><span class=\"token string\">선택된 도형: </span><span class=\"token interpolation\"><span class=\"token interpolation-punctuation punctuation\">${</span>figure<span class=\"token interpolation-punctuation punctuation\">}</span></span><span class=\"token template-punctuation string\">`</span></span><span class=\"token punctuation\">)</span><span class=\"token punctuation\">;</span>\n    \n    <span class=\"token keyword\">switch</span> <span class=\"token punctuation\">(</span>figure<span class=\"token punctuation\">)</span> <span class=\"token punctuation\">{</span>\n      <span class=\"token keyword\">case</span> <span class=\"token string\">\"정사각형\"</span><span class=\"token punctuation\">:</span>\n        rl<span class=\"token punctuation\">.</span><span class=\"token function\">question</span><span class=\"token punctuation\">(</span><span class=\"token string\">\"변의 길이를 입력 해 주세요. :\"</span><span class=\"token punctuation\">,</span> <span class=\"token parameter\">input</span> <span class=\"token operator\">=></span><span class=\"token punctuation\">{</span>\n        console<span class=\"token punctuation\">.</span><span class=\"token function\">log</span><span class=\"token punctuation\">(</span><span class=\"token function\">logInput</span><span class=\"token punctuation\">(</span>input<span class=\"token punctuation\">)</span><span class=\"token punctuation\">)</span><span class=\"token punctuation\">;</span>\n        console<span class=\"token punctuation\">.</span><span class=\"token function\">log</span><span class=\"token punctuation\">(</span><span class=\"token function\">logResult</span><span class=\"token punctuation\">(</span>figure<span class=\"token punctuation\">,</span> <span class=\"token function\">getSquareArea</span><span class=\"token punctuation\">(</span>input<span class=\"token punctuation\">)</span><span class=\"token punctuation\">)</span><span class=\"token punctuation\">)</span><span class=\"token punctuation\">;</span>\n        rl<span class=\"token punctuation\">.</span><span class=\"token function\">close</span><span class=\"token punctuation\">(</span><span class=\"token punctuation\">)</span><span class=\"token punctuation\">;</span>\n        <span class=\"token punctuation\">}</span><span class=\"token punctuation\">)</span><span class=\"token punctuation\">;</span>\n        <span class=\"token keyword\">break</span><span class=\"token punctuation\">;</span>\n        <span class=\"token keyword\">case</span> <span class=\"token string\">\"원\"</span><span class=\"token punctuation\">:</span>\n          rl<span class=\"token punctuation\">.</span><span class=\"token function\">question</span><span class=\"token punctuation\">(</span><span class=\"token string\">\"반지름의 길이를 입력 해 주세요. :\"</span><span class=\"token punctuation\">,</span> <span class=\"token parameter\">input</span> <span class=\"token operator\">=></span><span class=\"token punctuation\">{</span>\n          console<span class=\"token punctuation\">.</span><span class=\"token function\">log</span><span class=\"token punctuation\">(</span><span class=\"token function\">logInput</span><span class=\"token punctuation\">(</span>input<span class=\"token punctuation\">)</span><span class=\"token punctuation\">)</span><span class=\"token punctuation\">;</span>\n          console<span class=\"token punctuation\">.</span><span class=\"token function\">log</span><span class=\"token punctuation\">(</span><span class=\"token function\">logResult</span><span class=\"token punctuation\">(</span>figure<span class=\"token punctuation\">,</span> <span class=\"token function\">getCircleArea</span><span class=\"token punctuation\">(</span>input<span class=\"token punctuation\">)</span><span class=\"token punctuation\">)</span><span class=\"token punctuation\">)</span><span class=\"token punctuation\">;</span>\n          rl<span class=\"token punctuation\">.</span><span class=\"token function\">close</span><span class=\"token punctuation\">(</span><span class=\"token punctuation\">)</span><span class=\"token punctuation\">;</span>\n          <span class=\"token punctuation\">}</span><span class=\"token punctuation\">)</span><span class=\"token punctuation\">;</span>\n        <span class=\"token keyword\">break</span><span class=\"token punctuation\">;</span>\n      <span class=\"token keyword\">default</span><span class=\"token punctuation\">:</span>\n        console<span class=\"token punctuation\">.</span><span class=\"token function\">log</span><span class=\"token punctuation\">(</span>logFigureError<span class=\"token punctuation\">)</span><span class=\"token punctuation\">;</span>\n        rl<span class=\"token punctuation\">.</span><span class=\"token function\">close</span><span class=\"token punctuation\">(</span><span class=\"token punctuation\">)</span><span class=\"token punctuation\">;</span>\n    <span class=\"token punctuation\">}</span>\n  <span class=\"token punctuation\">}</span>\n<span class=\"token punctuation\">)</span><span class=\"token punctuation\">;</span></code></pre></div>","position":{"start":{"line":61,"column":1,"offset":1442},"end":{"line":97,"column":4,"offset":2400}}},{"type":"text","value":"\n"},{"type":"element","tagName":"p","properties":{},"children":[{"type":"text","value":"[index.js]","position":{"start":{"line":98,"column":2,"offset":2402},"end":{"line":98,"column":10,"offset":2410}}},{"type":"text","value":"파일과 ","position":{"start":{"line":98,"column":11,"offset":2411},"end":{"line":98,"column":15,"offset":2415}}},{"type":"text","value":"[mathUtil.js]","position":{"start":{"line":98,"column":16,"offset":2416},"end":{"line":98,"column":27,"offset":2427}}},{"type":"text","value":",","position":{"start":{"line":98,"column":28,"offset":2428},"end":{"line":98,"column":29,"offset":2429}}},{"type":"text","value":"[log.js]","position":{"start":{"line":98,"column":30,"offset":2430},"end":{"line":98,"column":36,"offset":2436}}},{"type":"text","value":"파일은 서로 의존성이 있는 파일로","position":{"start":{"line":98,"column":37,"offset":2437},"end":{"line":98,"column":55,"offset":2455}}},{"type":"element","tagName":"br","properties":{},"children":[],"position":{"start":{"line":98,"column":55,"offset":2455},"end":{"line":99,"column":1,"offset":2458}}},{"type":"text","value":"\n"},{"type":"text","value":"웹팩을 이용하 하나의 파일로 번들링 된다.","position":{"start":{"line":99,"column":1,"offset":2458},"end":{"line":99,"column":24,"offset":2481}}}],"position":{"start":{"line":98,"column":1,"offset":2401},"end":{"line":99,"column":24,"offset":2481}}},{"type":"text","value":"\n"},{"type":"element","tagName":"p","properties":{},"children":[{"type":"text","value":"이에 웹팩을 실행 하려면 이전 버젼의 웹팩에서는 설정해 주어야 했던 것들 을","position":{"start":{"line":101,"column":1,"offset":2483},"end":{"line":101,"column":43,"offset":2525}}},{"type":"element","tagName":"br","properties":{},"children":[],"position":{"start":{"line":101,"column":43,"offset":2525},"end":{"line":102,"column":1,"offset":2528}}},{"type":"text","value":"\n"},{"type":"text","value":"웹팩 4버젼으로 업데이트 된 후에 Zero Configuration을 통하여 자동으로 설정을 잡아주게 되었다. ","position":{"start":{"line":102,"column":1,"offset":2528},"end":{"line":102,"column":63,"offset":2590}}}],"position":{"start":{"line":101,"column":1,"offset":2483},"end":{"line":102,"column":63,"offset":2590}}},{"type":"text","value":"\n"},{"type":"element","tagName":"p","properties":{},"children":[{"type":"text","value":"대신 Zero Configuration을 사용하기 위해서는","position":{"start":{"line":104,"column":1,"offset":2592},"end":{"line":104,"column":33,"offset":2624}}},{"type":"element","tagName":"br","properties":{},"children":[],"position":{"start":{"line":104,"column":33,"offset":2624},"end":{"line":105,"column":1,"offset":2627}}},{"type":"text","value":"\n"},{"type":"text","value":"엔트리의 경로를 src폴더 안에 index.js라는 파일 이름으로 준비해 주어야 동작을 하고,","position":{"start":{"line":105,"column":1,"offset":2627},"end":{"line":105,"column":53,"offset":2679}}},{"type":"element","tagName":"br","properties":{},"children":[],"position":{"start":{"line":105,"column":53,"offset":2679},"end":{"line":106,"column":1,"offset":2682}}},{"type":"text","value":"\n"},{"type":"text","value":"또한 번들 파일의 위치도 dist라는 폴더 안으로 설정해주어야 하며 번들파일의 이름은 미리 main.js 로 정해져 있다.\n즉, entry와 output을 따로 설정 하지 않아도 자동으로 설정이 된다.","position":{"start":{"line":106,"column":1,"offset":2682},"end":{"line":107,"column":44,"offset":2794}}}],"position":{"start":{"line":104,"column":1,"offset":2592},"end":{"line":107,"column":44,"offset":2794}}},{"type":"text","value":"\n"},{"type":"element","tagName":"p","properties":{},"children":[{"type":"text","value":"이렇게 환경 설정을 해준 후","position":{"start":{"line":109,"column":1,"offset":2796},"end":{"line":109,"column":16,"offset":2811}}}],"position":{"start":{"line":109,"column":1,"offset":2796},"end":{"line":109,"column":16,"offset":2811}}},{"type":"text","value":"\n"},{"type":"raw","value":"<div class=\"gatsby-highlight\" data-language=\"shellscript\"><pre class=\"language-shellscript\"><code class=\"language-shellscript\">$ npx webpack --target=node</code></pre></div>","position":{"start":{"line":110,"column":1,"offset":2812},"end":{"line":112,"column":4,"offset":2859}}},{"type":"text","value":"\n"},{"type":"element","tagName":"p","properties":{},"children":[{"type":"raw","value":"<code class=\"language-text\">--target=node</code>","position":{"start":{"line":113,"column":1,"offset":2860},"end":{"line":113,"column":16,"offset":2875}}},{"type":"text","value":" 는 readline이라는 node의 내장 모듈을 인식할 수 있게 target키를 통해 node환경을 설정해주는 명령어이다.","position":{"start":{"line":113,"column":16,"offset":2875},"end":{"line":113,"column":85,"offset":2944}}}],"position":{"start":{"line":113,"column":1,"offset":2860},"end":{"line":113,"column":85,"offset":2944}}},{"type":"text","value":"\n"},{"type":"element","tagName":"h3","properties":{},"children":[{"type":"text","value":"Webpack 직접 설정하기","position":{"start":{"line":115,"column":5,"offset":2950},"end":{"line":115,"column":20,"offset":2965}}}],"position":{"start":{"line":115,"column":1,"offset":2946},"end":{"line":115,"column":20,"offset":2965}}},{"type":"text","value":"\n"},{"type":"element","tagName":"p","properties":{},"children":[{"type":"text","value":"[webpack.config.js]","position":{"start":{"line":116,"column":2,"offset":2967},"end":{"line":116,"column":19,"offset":2984}}}],"position":{"start":{"line":116,"column":1,"offset":2966},"end":{"line":116,"column":20,"offset":2985}}},{"type":"text","value":"\n"},{"type":"raw","value":"<div class=\"gatsby-highlight\" data-language=\"javascript\"><pre class=\"language-javascript\"><code class=\"language-javascript\"><span class=\"token keyword\">const</span> path <span class=\"token operator\">=</span> <span class=\"token function\">require</span><span class=\"token punctuation\">(</span><span class=\"token string\">'path'</span><span class=\"token punctuation\">)</span><span class=\"token punctuation\">;</span>\n\nmodule<span class=\"token punctuation\">.</span>exports <span class=\"token operator\">=</span> <span class=\"token punctuation\">{</span>\n    entry<span class=\"token punctuation\">:</span> <span class=\"token string\">'./src/index.js'</span><span class=\"token punctuation\">,</span>\n    output<span class=\"token punctuation\">:</span> <span class=\"token punctuation\">{</span>\n        path<span class=\"token punctuation\">:</span> path<span class=\"token punctuation\">.</span><span class=\"token function\">resolve</span><span class=\"token punctuation\">(</span>__dirname<span class=\"token punctuation\">,</span> <span class=\"token string\">'dist'</span><span class=\"token punctuation\">)</span><span class=\"token punctuation\">,</span>\n        filename<span class=\"token punctuation\">:</span> <span class=\"token string\">'bundle.js'</span> <span class=\"token comment\">// cli와 다르게 main.js가 아닌 bundle.js로 파일이 생성된다</span>\n    <span class=\"token punctuation\">}</span><span class=\"token punctuation\">,</span>\n    target<span class=\"token punctuation\">:</span> <span class=\"token string\">'node'</span>\n<span class=\"token punctuation\">}</span></code></pre></div>","position":{"start":{"line":117,"column":1,"offset":2986},"end":{"line":128,"column":4,"offset":3245}}},{"type":"text","value":"\n"},{"type":"element","tagName":"p","properties":{},"children":[{"type":"raw","value":"<br>","position":{"start":{"line":136,"column":1,"offset":3253},"end":{"line":136,"column":5,"offset":3257}}},{"type":"raw","value":"<br>","position":{"start":{"line":136,"column":5,"offset":3257},"end":{"line":136,"column":9,"offset":3261}}},{"type":"raw","value":"<br>","position":{"start":{"line":136,"column":9,"offset":3261},"end":{"line":136,"column":13,"offset":3265}}},{"type":"raw","value":"<br>","position":{"start":{"line":136,"column":13,"offset":3265},"end":{"line":136,"column":17,"offset":3269}}},{"type":"raw","value":"<br>","position":{"start":{"line":136,"column":17,"offset":3269},"end":{"line":136,"column":21,"offset":3273}}},{"type":"raw","value":"<br>","position":{"start":{"line":136,"column":21,"offset":3273},"end":{"line":136,"column":25,"offset":3277}}},{"type":"raw","value":"<br>","position":{"start":{"line":136,"column":25,"offset":3277},"end":{"line":136,"column":29,"offset":3281}}}],"position":{"start":{"line":136,"column":1,"offset":3253},"end":{"line":136,"column":29,"offset":3281}}},{"type":"text","value":"\n"},{"type":"element","tagName":"h6","properties":{},"children":[{"type":"text","value":"*위의 내용은 ","position":{"start":{"line":137,"column":7,"offset":3288},"end":{"line":137,"column":15,"offset":3296}}},{"type":"text","value":"[fastcampus]","position":{"start":{"line":137,"column":16,"offset":3297},"end":{"line":137,"column":26,"offset":3307}}},{"type":"text","value":"의 WEBPACK-백성훈 online 강의를 정리한 내용입니다.","position":{"start":{"line":137,"column":27,"offset":3308},"end":{"line":137,"column":62,"offset":3343}}}],"position":{"start":{"line":137,"column":1,"offset":3282},"end":{"line":137,"column":63,"offset":3344}}}],"position":{"start":{"line":1,"column":1,"offset":0},"end":{"line":138,"column":1,"offset":3345}}}}